bfprt/__init__.py
bfprt/algo.py
bfprt/types.py
bfprt-0.3.0.dist-info/METADATA
bfprt-0.3.0.dist-info/WHEEL
bfprt-0.3.0.dist-info/RECORD
